{
  "vehicles": {
    "Prius": {
      "milage": 4.8,
      "fuel": "E10"
    },
    "VW Beetle": {
      "milage": 7,
      "fuel": "P98"
    }
  },
  "locations": {
    "SBSHS": {
      "distance": 1.6
    },
    "Peregian Digital Hub": {
      "distance": 9.2
    },
    "Provectus Algae": {
      "distance": 8.8
    },
    "Noosa Civic": {
      "distance": 7.8
    },
    "Eumundi": {
      "distance": 21.8
    },
    "Cooroy": {
      "distance": 23.6
    },
    "Maroochydoore": {
      "distance": 33.2
    },
    "Brisbane": {
      "distance": 136.0
    }
  }
}

